djhx_blogger/__init__.py
djhx_blogger/__main__.py
djhx_blogger/cli.py
djhx_blogger/deploy.py
djhx_blogger/gen.py
djhx_blogger/log_config.py
djhx_blogger/static/css/archive.css
djhx_blogger/static/css/article.css
djhx_blogger/static/css/basic.css
djhx_blogger/static/css/category.css
djhx_blogger/static/images/favicon.ico
djhx_blogger/static/images/mountain.jpg
djhx_blogger/static/template/archive.html
djhx_blogger/static/template/article.html
djhx_blogger/static/template/category.html
djhx_blogger-0.1.12.dist-info/licenses/LICENSE
djhx_blogger-0.1.12.dist-info/METADATA
djhx_blogger-0.1.12.dist-info/WHEEL
djhx_blogger-0.1.12.dist-info/entry_points.txt
djhx_blogger-0.1.12.dist-info/top_level.txt
djhx_blogger-0.1.12.dist-info/RECORD
