Metadata-Version: 2.4
Name: djhx-blogger
Version: 0.1.12
Summary: A simple static site generator, support only markdown file.
Requires-Python: >=3.9
License-File: LICENSE
Requires-Dist: beautifulsoup4>=4.14.2
Requires-Dist: fabric>=3.2.2
Requires-Dist: jinja2>=3.1.6
Requires-Dist: markdown>=3.9
Requires-Dist: pillow>=11.3.0
Requires-Dist: platformdirs>=4.4.0
Requires-Dist: typer>=0.20.0
Dynamic: license-file
